{
  "horizon": "1block",
  "xgb_metrics": {
    "horizon_blocks": 1,
    "mse": 0.055403679551569475,
    "rmse": 0.23537986224732454,
    "mae": 0.21098546187082926,
    "r2": 0.0,
    "block_inclusion_accuracy": 0.6666666666666666,
    "avg_overpay_sat_vb": 0.16329248746236166,
    "median_overpay_sat_vb": 0.1535099744796753,
    "avg_underpay_sat_vb": 0.04769297440846761,
    "overpay_mape": 8.164624373118084,
    "within_10pct": 0.5,
    "within_20pct": 1.0,
    "within_50pct": 1.0,
    "asymmetric_loss": 0.019357083368043485,
    "mape": 10.549273093541462
  },
  "lgb_metrics": {
    "horizon_blocks": 1,
    "model_type": "lightgbm",
    "mse": 0.8357114581670902,
    "rmse": 0.9141725538250918,
    "mae": 0.9141725538250917,
    "r2": 0.0,
    "block_inclusion_accuracy": 0.0,
    "avg_overpay_sat_vb": 0.0,
    "avg_underpay_sat_vb": 0.9141725538250917,
    "within_10pct": 0.0,
    "within_20pct": 0.0,
    "within_50pct": 1.0,
    "asymmetric_loss": 0.584998020716963,
    "mape": 45.708627691254584
  }
}