{
  "timestamp": "2026-04-27T15:14:52.644189",
  "duration_seconds": 1.233537,
  "xgb_results": {
    "1block": {
      "horizon_blocks": 1,
      "mse": 0.2236319808132876,
      "rmse": 0.4728974315993772,
      "mae": 0.45664026339848834,
      "r2": 0.0,
      "block_inclusion_accuracy": 0.0,
      "avg_overpay_sat_vb": 0.0,
      "median_overpay_sat_vb": 0.0,
      "avg_underpay_sat_vb": 0.45664026339848834,
      "overpay_mape": 0.0,
      "within_10pct": 0.0,
      "within_20pct": 0.3333333333333333,
      "within_50pct": 1.0,
      "asymmetric_loss": 0.1565423865693013,
      "mape": 22.832013169924416
    },
    "3block": {
      "horizon_blocks": 3,
      "mse": 0.5285101093196664,
      "rmse": 0.7269870076690961,
      "mae": 0.688739558060964,
      "r2": 0.0,
      "block_inclusion_accuracy": 0.0,
      "avg_overpay_sat_vb": 0.0,
      "median_overpay_sat_vb": 0.0,
      "avg_underpay_sat_vb": 0.688739558060964,
      "overpay_mape": 0.0,
      "within_10pct": 0.0,
      "within_20pct": 0.3333333333333333,
      "within_50pct": 1.0,
      "asymmetric_loss": 0.36995707652376647,
      "mape": 34.4369779030482
    },
    "6block": {
      "horizon_blocks": 6,
      "mse": 0.5285101093196664,
      "rmse": 0.7269870076690961,
      "mae": 0.688739558060964,
      "r2": 0.0,
      "block_inclusion_accuracy": 0.0,
      "avg_overpay_sat_vb": 0.0,
      "median_overpay_sat_vb": 0.0,
      "avg_underpay_sat_vb": 0.688739558060964,
      "overpay_mape": 0.0,
      "within_10pct": 0.0,
      "within_20pct": 0.3333333333333333,
      "within_50pct": 1.0,
      "asymmetric_loss": 0.36995707652376647,
      "mape": 34.4369779030482
    }
  },
  "lgb_results": {
    "1block": {
      "horizon_blocks": 1,
      "model_type": "lightgbm",
      "mse": 0.8357114581670902,
      "rmse": 0.9141725538250918,
      "mae": 0.9141725538250917,
      "r2": 0.0,
      "block_inclusion_accuracy": 0.0,
      "avg_overpay_sat_vb": 0.0,
      "avg_underpay_sat_vb": 0.9141725538250917,
      "within_10pct": 0.0,
      "within_20pct": 0.0,
      "within_50pct": 1.0,
      "asymmetric_loss": 0.584998020716963,
      "mape": 45.708627691254584
    },
    "3block": {
      "horizon_blocks": 3,
      "model_type": "lightgbm",
      "mse": 0.9918380673985933,
      "rmse": 0.9959106723991832,
      "mae": 0.9959106723991834,
      "r2": 0.0,
      "block_inclusion_accuracy": 0.0,
      "avg_overpay_sat_vb": 0.0,
      "avg_underpay_sat_vb": 0.9959106723991834,
      "within_10pct": 0.0,
      "within_20pct": 0.0,
      "within_50pct": 1.0,
      "asymmetric_loss": 0.6942866471790153,
      "mape": 49.79553361995917
    },
    "6block": {
      "horizon_blocks": 6,
      "model_type": "lightgbm",
      "mse": 1.0,
      "rmse": 1.0,
      "mae": 1.0,
      "r2": 0.0,
      "block_inclusion_accuracy": 0.0,
      "avg_overpay_sat_vb": 0.0,
      "avg_underpay_sat_vb": 1.0,
      "within_10pct": 0.0,
      "within_20pct": 0.0,
      "within_50pct": 0.0,
      "asymmetric_loss": 0.7000000000000001,
      "mape": 50.0
    }
  }
}