{
  "timestamp": "2026-05-26T00:12:42.473277",
  "duration_seconds": 3.470787,
  "xgb_results": {
    "1block": {
      "horizon_blocks": 1,
      "mse": 1.8050253873955928,
      "rmse": 1.3435123324315237,
      "mae": 1.319985071818034,
      "r2": 0.0,
      "block_inclusion_accuracy": 1.0,
      "avg_overpay_sat_vb": 1.319985071818034,
      "median_overpay_sat_vb": 1.2141685485839844,
      "avg_underpay_sat_vb": 0.0,
      "overpay_mape": 65.9992535909017,
      "within_10pct": 0.0,
      "within_20pct": 0.0,
      "within_50pct": 0.0,
      "asymmetric_loss": 0.5415076162186779,
      "mape": 65.9992535909017
    },
    "3block": {
      "horizon_blocks": 3,
      "mse": 1.9000603892027261,
      "rmse": 1.3784267805011357,
      "mae": 1.2417614857355754,
      "r2": 0.0,
      "block_inclusion_accuracy": 1.0,
      "avg_overpay_sat_vb": 1.2417614857355754,
      "median_overpay_sat_vb": 1.1560782194137573,
      "avg_underpay_sat_vb": 0.0,
      "overpay_mape": 62.08807428677877,
      "within_10pct": 0.0,
      "within_20pct": 0.0,
      "within_50pct": 0.5,
      "asymmetric_loss": 0.5700181167608179,
      "mape": 62.08807428677877
    },
    "6block": {
      "horizon_blocks": 6,
      "mse": 1.9000603892027261,
      "rmse": 1.3784267805011357,
      "mae": 1.2417614857355754,
      "r2": 0.0,
      "block_inclusion_accuracy": 1.0,
      "avg_overpay_sat_vb": 1.2417614857355754,
      "median_overpay_sat_vb": 1.1560782194137573,
      "avg_underpay_sat_vb": 0.0,
      "overpay_mape": 62.08807428677877,
      "within_10pct": 0.0,
      "within_20pct": 0.0,
      "within_50pct": 0.5,
      "asymmetric_loss": 0.5700181167608179,
      "mape": 62.08807428677877
    }
  },
  "lgb_results": {
    "1block": {
      "horizon_blocks": 1,
      "model_type": "lightgbm",
      "mse": 0.7458370089727663,
      "rmse": 0.8636185552503873,
      "mae": 0.8636185552503871,
      "r2": 0.0,
      "block_inclusion_accuracy": 0.0,
      "avg_overpay_sat_vb": 0.0,
      "avg_underpay_sat_vb": 0.8636185552503871,
      "within_10pct": 0.0,
      "within_20pct": 0.0,
      "within_50pct": 1.0,
      "asymmetric_loss": 0.5220859062809363,
      "mape": 43.18092776251935
    },
    "3block": {
      "horizon_blocks": 3,
      "model_type": "lightgbm",
      "mse": 1.0,
      "rmse": 1.0,
      "mae": 1.0,
      "r2": 0.0,
      "block_inclusion_accuracy": 0.0,
      "avg_overpay_sat_vb": 0.0,
      "avg_underpay_sat_vb": 1.0,
      "within_10pct": 0.0,
      "within_20pct": 0.0,
      "within_50pct": 0.0,
      "asymmetric_loss": 0.7000000000000001,
      "mape": 50.0
    },
    "6block": {
      "horizon_blocks": 6,
      "model_type": "lightgbm",
      "mse": 1.0,
      "rmse": 1.0,
      "mae": 1.0,
      "r2": 0.0,
      "block_inclusion_accuracy": 0.0,
      "avg_overpay_sat_vb": 0.0,
      "avg_underpay_sat_vb": 1.0,
      "within_10pct": 0.0,
      "within_20pct": 0.0,
      "within_50pct": 0.0,
      "asymmetric_loss": 0.7000000000000001,
      "mape": 50.0
    }
  }
}